LICENSE
MANIFEST.in
README.md
README.rst
VERSION
requirements.txt
setup.py
bin/penelope
penelope/__init__.py
penelope/__main__.py
penelope/collation_default.py
penelope/collation_german.py
penelope/command_line.py
penelope/dictionary.py
penelope/dictionary_ebook.py
penelope/format_bookeen.py
penelope/format_csv.py
penelope/format_epub.py
penelope/format_kobo.py
penelope/format_mobi.py
penelope/format_stardict.py
penelope/format_xml.py
penelope/input_parser_identity.py
penelope/input_parser_webster.py
penelope/prefix_default.py
penelope/prefix_kobo.py
penelope/utilities.py
penelope.egg-info/PKG-INFO
penelope.egg-info/SOURCES.txt
penelope.egg-info/dependency_links.txt
penelope.egg-info/requires.txt
penelope.egg-info/top_level.txt
penelope/res/StarDictFileFormat.txt
penelope/res/dictionary.dtd
penelope/res/empty.idx