Metadata-Version: 1.1
Name: penelope
Version: 3.1.2.0
Summary: Penelope is a multi-tool for creating, editing and converting dictionaries, especially for eReader devices
Home-page: https://github.com/pettarin/penelope
Author: Alberto Pettarin
Author-email: alberto@albertopettarin.it
License: MIT License
Keywords: Dictionary,Dictionaries,Index,Merge,Flatten,eReader,eReaders,Bookeen,CSV,EPUB,MOBI,Kindle,Kobo,StarDict,XML,MARISA,kindlegen,dictzip
Platform: UNKNOWN
Classifier: Development Status :: 5 - Production/Stable
Classifier: Environment :: Console
Classifier: Intended Audience :: Developers
Classifier: Intended Audience :: End Users/Desktop
Classifier: License :: OSI Approved :: MIT License
Classifier: Natural Language :: English
Classifier: Operating System :: MacOS :: MacOS X
Classifier: Operating System :: Microsoft :: Windows
Classifier: Operating System :: POSIX :: Linux
Classifier: Programming Language :: Python
Classifier: Programming Language :: Python :: 2
Classifier: Programming Language :: Python :: 2.7
Classifier: Programming Language :: Python :: 3
Classifier: Programming Language :: Python :: 3.4
Classifier: Programming Language :: Python :: 3.5
Classifier: Topic :: Desktop Environment
Classifier: Topic :: Documentation
Classifier: Topic :: Office/Business
Classifier: Topic :: Software Development :: Internationalization
Classifier: Topic :: Software Development :: Localization
Classifier: Topic :: Text Editors
Classifier: Topic :: Text Editors :: Text Processing
Classifier: Topic :: Text Processing
Classifier: Topic :: Text Processing :: General
Classifier: Topic :: Text Processing :: Indexing
Classifier: Topic :: Text Processing :: Linguistic
Classifier: Topic :: Text Processing :: Markup
Classifier: Topic :: Text Processing :: Markup :: HTML
Classifier: Topic :: Text Processing :: Markup :: XML
Classifier: Topic :: Utilities
